LICENSE
setup.py
pyrfuniverse_test/__init__.py
pyrfuniverse_test/entry_points.py
pyrfuniverse_test.egg-info/PKG-INFO
pyrfuniverse_test.egg-info/SOURCES.txt
pyrfuniverse_test.egg-info/dependency_links.txt
pyrfuniverse_test.egg-info/entry_points.txt
pyrfuniverse_test.egg-info/requires.txt
pyrfuniverse_test.egg-info/top_level.txt
pyrfuniverse_test/__pycache__/__init__.cpython-310.pyc
pyrfuniverse_test/__pycache__/__init__.cpython-312.pyc
pyrfuniverse_test/__pycache__/__init__.cpython-38.pyc
pyrfuniverse_test/extend/__init__.py
pyrfuniverse_test/extend/activelightsensor_attr.py
pyrfuniverse_test/extend/digit_attr.py
pyrfuniverse_test/extend/gelslim_attr.py
pyrfuniverse_test/extend/graspsim_attr.py
pyrfuniverse_test/extend/humanbody_attr.py
pyrfuniverse_test/extend/omplmanager_attr.py
pyrfuniverse_test/extend/softbody_attr.py
pyrfuniverse_test/extend/__pycache__/__init__.cpython-310.pyc
pyrfuniverse_test/extend/__pycache__/__init__.cpython-312.pyc
pyrfuniverse_test/extend/__pycache__/activelightsensor_attr.cpython-310.pyc
pyrfuniverse_test/extend/__pycache__/digit_attr.cpython-310.pyc
pyrfuniverse_test/extend/__pycache__/gelslim_attr.cpython-310.pyc
pyrfuniverse_test/extend/__pycache__/graspsim_attr.cpython-310.pyc
pyrfuniverse_test/extend/__pycache__/humanbody_attr.cpython-310.pyc
pyrfuniverse_test/extend/__pycache__/omplmanager_attr.cpython-310.pyc
pyrfuniverse_test/extend/__pycache__/omplmanager_attr.cpython-312.pyc
pyrfuniverse_test/mesh/000000_000673513312.ply
pyrfuniverse_test/mesh/Tshirt.obj
pyrfuniverse_test/mesh/002_master_chef_can/google_16k/texture_map.png
pyrfuniverse_test/mesh/002_master_chef_can/google_16k/textured.mtl
pyrfuniverse_test/mesh/002_master_chef_can/google_16k/textured.obj
pyrfuniverse_test/mesh/drink1/drink1.obj
pyrfuniverse_test/mesh/drink1/drink1.ply
pyrfuniverse_test/mesh/drink1/grasps.csv
pyrfuniverse_test/mesh/drink1/grasps_rfu.csv
pyrfuniverse_test/mesh/drink1/grasps_scene.obj
pyrfuniverse_test/mesh/drink1/grasps_xyz.ply
pyrfuniverse_test/mesh/drink1/material_0.jpeg
pyrfuniverse_test/mesh/drink1/material_0.mtl
pyrfuniverse_test/test/__init__.py
pyrfuniverse_test/test/test_active_depth.py
pyrfuniverse_test/test/test_articulation_ik.py
